{"ok":true,"result":[{"update_id":696490412,
"message":{"message_id":2408,"from":{"id":178185844,"first_name":"Yovan","last_name":"Keswani","username":"yovankeswani"},"chat":{"id":178185844,"first_name":"Yovan","last_name":"Keswani","username":"yovankeswani","type":"private"},"date":1474264111,"location":{"latitude":-6.182298,"longitude":106.750237}}},{"update_id":696490413,
"message":{"message_id":2409,"from":{"id":178185844,"first_name":"Yovan","last_name":"Keswani","username":"yovankeswani"},"chat":{"id":178185844,"first_name":"Yovan","last_name":"Keswani","username":"yovankeswani","type":"private"},"date":1474264118,"text":"\/menu","entities":[{"type":"bot_command","offset":0,"length":5}]}},{"update_id":696490414,
"message":{"message_id":2410,"from":{"id":178185844,"first_name":"Yovan","last_name":"Keswani","username":"yovankeswani"},"chat":{"id":178185844,"first_name":"Yovan","last_name":"Keswani","username":"yovankeswani","type":"private"},"date":1474264124,"text":"\/view_2190","entities":[{"type":"bot_command","offset":0,"length":10}]}}]}